[
  {
    "id": 1,
    "question": "What is RewaCitty?",
    "answer": "RewaCitty is a digital real estate platform that helps users find, list, and manage properties with ease."
  },
  {
    "id": 2,
    "question": "How do I create an account?",
    "answer": "You can create an account by clicking the Sign Up button and providing your basic personal information."
  },
  {
    "id": 3,
    "question": "Is RewaCitty free to use?",
    "answer": "Yes, browsing properties is completely free. Premium features may require a subscription."
  },
  {
    "id": 4,
    "question": "How do I list my property?",
    "answer": "Go to your dashboard and select 'Add Property'. Fill in the required details and upload high-quality photos."
  },
  {
    "id": 5,
    "question": "Can I edit my property listing?",
    "answer": "Yes, you can edit any property listing from your dashboard by selecting the 'Edit' option."
  },
  {
    "id": 6,
    "question": "How do I contact an agent?",
    "answer": "Each property page includes an option to message or call the assigned agent directly."
  },
  {
    "id": 7,
    "question": "Are the property prices negotiable?",
    "answer": "Price negotiations depend on the property owner or agent handling the listing."
  },
  {
    "id": 8,
    "question": "Can I schedule a property tour?",
    "answer": "Yes, you can request a virtual or physical property tour from the property page."
  },
  {
    "id": 9,
    "question": "Does RewaCitty verify all listed properties?",
    "answer": "We perform verification on most listings, but users are encouraged to conduct additional checks."
  },
  {
    "id": 10,
    "question": "How do I reset my password?",
    "answer": "Click on 'Forgot Password' at login and follow the instructions sent to your email."
  },
  {
    "id": 11,
    "question": "Can I save properties for later?",
    "answer": "Yes, you can bookmark properties and access them anytime from your saved list."
  },
  {
    "id": 12,
    "question": "Does RewaCitty offer mortgage assistance?",
    "answer": "We provide mortgage calculators and connect users with trusted financial lenders."
  },
  {
    "id": 13,
    "question": "How accurate are the property details?",
    "answer": "All details are provided by property owners and agents, and we try to ensure maximum accuracy."
  },
  {
    "id": 14,
    "question": "How do I delete my account?",
    "answer": "You can request account deletion from the settings page or contact customer support."
  },
  {
    "id": 15,
    "question": "Can I report a fraudulent listing?",
    "answer": "Yes, each listing has a 'Report' button that allows users to submit fraud concerns."
  },
  {
    "id": 16,
    "question": "Which locations do you cover?",
    "answer": "RewaCitty covers major cities and towns, and we are constantly expanding to more areas."
  },
  {
    "id": 17,
    "question": "Can I advertise my real estate agency on RewaCitty?",
    "answer": "Yes, agencies can partner with us for advertising and premium features."
  },
  {
    "id": 18,
    "question": "Does RewaCitty offer customer support?",
    "answer": "We offer 24/7 customer support via email, chat, and phone."
  },
  {
    "id": 19,
    "question": "Are there hidden fees when buying a property?",
    "answer": "RewaCitty does not charge hidden fees, but additional charges may come from agents or legal services."
  },
  {
    "id": 20,
    "question": "How do I update my profile information?",
    "answer": "Navigate to your profile settings and update your personal information anytime."
  },
  {
    "id": 21,
    "question": "Can I rent properties using RewaCitty?",
    "answer": "Yes, we support both rental and purchase property listings."
  },
  {
    "id": 22,
    "question": "How long does property approval take?",
    "answer": "Property listings are typically reviewed and approved within 24–48 hours."
  },
  {
    "id": 23,
    "question": "What file types can I upload for property images?",
    "answer": "We support JPG, PNG, and WEBP image formats."
  },
  {
    "id": 24,
    "question": "Can I list commercial properties?",
    "answer": "Yes, RewaCitty supports residential, commercial, and land listings."
  },
  {
    "id": 25,
    "question": "Is my personal data secure?",
    "answer": "We prioritize user privacy and use industry-standard encryption to secure your data."
  },
  {
    "id": 26,
    "question": "Can I chat directly with agents in real-time?",
    "answer": "Our platform includes a live chat feature for quick communication with agents."
  },
  {
    "id": 27,
    "question": "Do you offer property valuation services?",
    "answer": "Yes, we provide automated valuation tools and partner with certified valuers."
  },
  {
    "id": 28,
    "question": "Can international users access RewaCitty?",
    "answer": "Yes, RewaCitty is accessible worldwide and supports global users."
  },
  {
    "id": 29,
    "question": "Do you provide neighborhood insights?",
    "answer": "Yes, each property page includes insights on schools, transport, and local amenities."
  },
  {
    "id": 30,
    "question": "How often are property listings updated?",
    "answer": "Listings are updated every day to ensure accurate and current information."
  }
]
